{
  "model": {
    "type": "minecraft:select",
    "block_state_property": "age",
    "cases": [
      {
        "model": {
          "type": "minecraft:model",
          "model": "minecraft:block/spore_blossom_stage_0_closed"
        },
        "when": "0"
      },
      {
        "model": {
          "type": "minecraft:model",
          "model": "minecraft:block/spore_blossom_stage_1_ajar"
        },
        "when": "1"
      },
      {
        "model": {
          "type": "minecraft:model",
          "model": "minecraft:block/spore_blossom_stage_2_partial"
        },
        "when": "2"
      },
      {
        "model": {
          "type": "minecraft:model",
          "model": "minecraft:block/spore_blossom_stage_3_full"
        },
        "when": "3"
      }
    ],
    "fallback": {
      "type": "minecraft:model",
      "model": "minecraft:block/spore_blossom_stage_3_full"
    },
    "property": "minecraft:block_state"
  }
}